fastannoy/__init__.py
fastannoy/__init__.pyi
fastannoy/annoylib.cpython-39-darwin.so
fastannoy/py.typed
fastannoy-1.1.1.dist-info/LICENSE
fastannoy-1.1.1.dist-info/METADATA
fastannoy-1.1.1.dist-info/WHEEL
fastannoy-1.1.1.dist-info/top_level.txt
fastannoy-1.1.1.dist-info/RECORD
