Metadata-Version: 2.1
Name: fastannoy
Version: 1.1.1
Summary: Faster version of Approximate Nearest Neighbors in C++/Python optimized for memory usage and loading/saving to disk.
Home-page: https://github.com/QunBB/fastannoy
Author: Qun
Author-email: myqun20190810@163.com
License: Apache License 2.0
Keywords: nns,approximate nearest neighbor search
Classifier: Development Status :: 5 - Production/Stable
Classifier: Programming Language :: Python
Classifier: Programming Language :: Python :: 2.7
Classifier: Programming Language :: Python :: 3.3
Classifier: Programming Language :: Python :: 3.4
Classifier: Programming Language :: Python :: 3.5
Classifier: Programming Language :: Python :: 3.6
Classifier: Programming Language :: Python :: 3.7
Classifier: Programming Language :: Python :: 3.8
Classifier: Programming Language :: Python :: 3.9
Classifier: Programming Language :: Python :: 3.10
Classifier: Programming Language :: Python :: 3.11
Classifier: Programming Language :: Python :: 3.12
Requires-Python: >=2.7
License-File: LICENSE
